{"chrome://browser/content/browser.xhtml":{"main-window":{"sizemode":"maximized","screenX":"0","screenY":"0","width":"1920","height":"1080"},"vertical-tabs":{"collapsed":"true"},"TabsToolbar":{"collapsed":"false"}},"chrome://global/content/pictureinpicture/player.xhtml":{"picture-in-picture":{"left":"0","top":"0","width":"523","height":"294"}},"chrome://browser/content/places/places.xhtml":{"placesContentTags":{"ordinal":"3"},"placesContentUrl":{"ordinal":"5"},"placesContentDate":{"ordinal":"7","sortDirection":"descending"},"placesContentVisitCount":{"ordinal":"9"},"placesContentDateAdded":{"ordinal":"11"},"placesContentLastModified":{"ordinal":"13"},"places":{"sizemode":"maximized","screenX":"0","screenY":"0","width":"1","height":"1"},"placesContentTitle":{"sortDirection":"-moz-missing\n"}}}